{
    "batch": {
        "batchLabel": "v6_batch5",
        "cfgFile": "cfg.py",
        "evolCfg": {
            "fitnessFunc": "removed"
        },
        "initCfg": {},
        "method": "grid",
        "netParamsFile": "netParams.py",
        "params": [
            {
                "label": "rateStimI",
                "values": [
                    9.0
                ]
            },
            {
                "label": "rateStimE",
                "values": [
                    9.0
                ]
            }
        ],
        "runCfg": {
            "cores": 6,
            "mpiCommand": "mpiexec",
            "script": "init.py",
            "skip": true,
            "type": "mpi_direct"
        },
        "saveFolder": "../data/v6_batch5",
        "seed": null
    }
}