{
    "conds": {
        "cellModel": "HH_full",
        "cellType": "L23_BP_cNA"
    },
    "diversityFraction": 0.25,
    "globals": {},
    "secLists": {
        "SectionList[0]": [],
        "SectionList[1]": [],
        "all": [
            "soma",
            "dend_0",
            "dend_1",
            "dend_2",
            "dend_3",
            "dend_4",
            "dend_5",
            "dend_6",
            "dend_7",
            "dend_8",
            "dend_9",
            "dend_10",
            "dend_11",
            "axon_0",
            "axon_1"
        ],
        "apical": [],
        "axonal": [
            "axon_0",
            "axon_1"
        ],
        "basal": [
            "dend_0",
            "dend_1",
            "dend_2",
            "dend_3",
            "dend_4",
            "dend_5",
            "dend_6",
            "dend_7",
            "dend_8",
            "dend_9",
            "dend_10",
            "dend_11"
        ],
        "somatic": [
            "soma"
        ],
        "spiny": [
            "soma",
            "dend_0",
            "dend_1",
            "dend_2",
            "dend_3",
            "dend_4",
            "dend_5",
            "dend_6",
            "dend_7",
            "dend_8",
            "dend_9",
            "dend_10",
            "dend_11"
        ],
        "spinyEE": [
            "dend_0",
            "dend_1",
            "dend_2",
            "dend_3",
            "dend_4",
            "dend_5",
            "dend_6",
            "dend_7",
            "dend_8",
            "dend_9",
            "dend_10",
            "dend_11"
        ]
    },
    "secs": {
        "axon_0": {
            "geom": {
                "L": 30.0,
                "Ra": 100.0,
                "cm": 1.0,
                "diam": 0.5500000119209293,
                "nseg": 1
            },
            "ions": {
                "ca": {
                    "e": 132.4579341637009,
                    "i": 5e-05,
                    "o": 2.0
                },
                "k": {
                    "e": -85.0,
                    "i": 54.4,
                    "o": 2.5
                },
                "na": {
                    "e": 50.0,
                    "i": 10.0,
                    "o": 140.0
                }
            },
            "mechs": {
                "Ca": {
                    "gCabar": 3e-06
                },
                "CaDynamics_E2": {
                    "decay": 64.27799,
                    "depth": 0.1,
                    "gamma": 0.010353,
                    "minCai": 0.0001
                },
                "Ca_LVAst": {
                    "gCa_LVAstbar": 1.5e-05
                },
                "Im": {
                    "gImbar": 0.000999
                },
                "K_Pst": {
                    "gK_Pstbar": 0.004729
                },
                "K_Tst": {
                    "gK_Tstbar": 0.098908
                },
                "NaTa_t": {
                    "gNaTa_tbar": 3.959764
                },
                "Nap_Et2": {
                    "gNap_Et2bar": 0.0
                },
                "SK_E2": {
                    "gSK_E2bar": 0.003442
                },
                "SKv3_1": {
                    "gSKv3_1bar": 0.317363
                },
                "pas": {
                    "e": -60.21651,
                    "g": 9.4e-05
                }
            },
            "topol": {
                "childX": 0.0,
                "parentSec": "soma",
                "parentX": 1.0
            }
        },
        "axon_1": {
            "geom": {
                "L": 30.0,
                "Ra": 100.0,
                "cm": 1.0,
                "diam": 0.5500000119209293,
                "nseg": 1
            },
            "ions": {
                "ca": {
                    "e": 132.4579341637009,
                    "i": 5e-05,
                    "o": 2.0
                },
                "k": {
                    "e": -85.0,
                    "i": 54.4,
                    "o": 2.5
                },
                "na": {
                    "e": 50.0,
                    "i": 10.0,
                    "o": 140.0
                }
            },
            "mechs": {
                "Ca": {
                    "gCabar": 3e-06
                },
                "CaDynamics_E2": {
                    "decay": 64.27799,
                    "depth": 0.1,
                    "gamma": 0.010353,
                    "minCai": 0.0001
                },
                "Ca_LVAst": {
                    "gCa_LVAstbar": 1.5e-05
                },
                "Im": {
                    "gImbar": 0.000999
                },
                "K_Pst": {
                    "gK_Pstbar": 0.004729
                },
                "K_Tst": {
                    "gK_Tstbar": 0.098908
                },
                "NaTa_t": {
                    "gNaTa_tbar": 3.959764
                },
                "Nap_Et2": {
                    "gNap_Et2bar": 0.0
                },
                "SK_E2": {
                    "gSK_E2bar": 0.003442
                },
                "SKv3_1": {
                    "gSKv3_1bar": 0.317363
                },
                "pas": {
                    "e": -60.21651,
                    "g": 9.4e-05
                }
            },
            "topol": {
                "childX": 0.0,
                "parentSec": "axon_0",
                "parentX": 1.0
            }
        },
        "dend_0": {
            "geom": {
                "L": 9.006126455158277,
                "Ra": 100.0,
                "cm": 1.0,
                "diam": 1.0406415221417609,
                "nseg": 1,
                "pt3d": [
                    [
                        0.7789497822523117,
                        8.715841293334961,
                        -0.7348316311836243,
                        1.3899999856948853
                    ],
                    [
                        0.7898987382650375,
                        14.972360610961914,
                        1.8650883436203003,
                        0.8299999833106995
                    ],
                    [
                        0.7935037463903427,
                        17.032461166381836,
                        2.721168279647827,
                        0.8299999833106995
                    ]
                ]
            },
            "ions": {
                "k": {
                    "e": -85.0,
                    "i": 54.4,
                    "o": 2.5
                },
                "na": {
                    "e": 50.0,
                    "i": 10.0,
                    "o": 140.0
                }
            },
            "mechs": {
                "Ih": {
                    "gIhbar": 6.910303075419812e-05
                },
                "Im": {
                    "gImbar": 8e-06
                },
                "K_Pst": {
                    "gK_Pstbar": 1e-05
                },
                "K_Tst": {
                    "gK_Tstbar": 0.0095
                },
                "NaTs2_t": {
                    "gNaTs2_tbar": 1e-05
                },
                "Nap_Et2": {
                    "gNap_Et2bar": 1e-06
                },
                "SKv3_1": {
                    "gSKv3_1bar": 0.004399
                },
                "pas": {
                    "e": -79.31574,
                    "g": 1e-06
                }
            },
            "topol": {
                "childX": 0.0,
                "parentSec": "soma",
                "parentX": 0.5
            }
        },
        "dend_1": {
            "geom": {
                "L": 116.24889625241833,
                "Ra": 100.0,
                "cm": 1.0,
                "diam": 0.8299999833106994,
                "nseg": 5,
                "pt3d": [
                    [
                        0.7935037463903427,
                        17.032461166381836,
                        2.721168279647827,
                        0.8299999833106995
                    ],
                    [
                        1.9936097115278244,
                        20.13176155090332,
                        3.3159384727478027,
                        0.8299999833106995
                    ],
                    [
                        2.923599883913994,
                        22.572860717773438,
                        3.886578321456909,
                        0.8299999833106995
                    ],
                    [
                        4.358299896121025,
                        26.41676139831543,
                        4.941718339920044,
                        0.8299999833106995
                    ],
                    [
                        5.721629783511162,
                        30.119060516357422,
                        6.006168603897095,
                        0.8299999833106995
                    ],
                    [
                        7.2426697462797165,
                        34.79616165161133,
                        7.244378328323364,
                        0.8299999833106995
                    ],
                    [
                        8.343479797244072,
                        38.32136154174805,
                        8.098648309707642,
                        0.8299999833106995
                    ],
                    [
                        9.095789596438408,
                        40.98186111450195,
                        8.790198564529419,
                        0.8299999833106995
                    ],
                    [
                        9.84866015613079,
                        43.898162841796875,
                        9.475008249282837,
                        0.8299999833106995
                    ],
                    [
                        10.004959747195244,
                        44.68986129760742,
                        9.636708498001099,
                        0.8299999833106995
                    ],
                    [
                        11.582949325442314,
                        53.78996276855469,
                        11.076868295669556,
                        0.8299999833106995
                    ],
                    [
                        11.826149627566338,
                        55.72146224975586,
                        11.289968729019165,
                        0.8299999833106995
                    ],
                    [
                        12.075850173830986,
                        58.34626007080078,
                        11.471068620681763,
                        0.8299999833106995
                    ],
                    [
                        12.248550102114677,
                        60.616859436035156,
                        11.592968225479126,
                        0.8299999833106995
                    ],
                    [
                        12.392949745059013,
                        63.24736022949219,
                        11.713868379592896,
                        0.8299999833106995
                    ],
                    [
                        12.597949668765068,
                        66.57156372070312,
                        11.858068704605103,
                        0.8299999833106995
                    ],
                    [
                        12.72745005786419,
                        69.99126434326172,
                        12.031168222427368,
                        0.8299999833106995
                    ],
                    [
                        12.832850143313408,
                        71.94715881347656,
                        12.117968797683716,
                        0.8299999833106995
                    ],
                    [
                        13.06644980609417,
                        74.97746276855469,
                        12.215667963027954,
                        0.8299999833106995
                    ],
                    [
                        13.2555500715971,
                        77.95416259765625,
                        12.337368249893188,
                        0.8299999833106995
                    ],
                    [
                        13.48624961078167,
                        81.0859603881836,
                        12.412267923355103,
                        0.8299999833106995
                    ],
                    [
                        13.805549308657646,
                        85.17896270751953,
                        12.548768281936646,
                        0.8299999833106995
                    ],
                    [
                        14.067149803042412,
                        87.85285949707031,
                        12.74396824836731,
                        0.8299999833106995
                    ],
                    [
                        14.204950019717216,
                        89.33076477050781,
                        12.89866852760315,
                        0.8299999833106995
                    ],
                    [
                        14.368449851870537,
                        91.00035858154297,
                        13.161068201065063,
                        0.8299999833106995
                    ],
                    [
                        14.670049354434013,
                        93.4703598022461,
                        13.678568124771118,
                        0.8299999833106995
                    ],
                    [
                        15.07114951312542,
                        97.08656311035156,
                        14.70546841621399,
                        0.550000011920929
                    ],
                    [
                        15.69875018298626,
                        101.83045959472656,
                        16.212969064712524,
                        0.550000011920929
                    ],
                    [
                        15.831450149416924,
                        103.22245788574219,
                        16.7064688205719,
                        0.550000011920929
                    ],
                    [
                        16.092449828982353,
                        106.1474609375,
                        17.734169244766235,
                        0.550000011920929
                    ],
                    [
                        16.166049644351006,
                        107.3714599609375,
                        18.1616690158844,
                        0.550000011920929
                    ],
                    [
                        16.268849059939384,
                        109.66445922851562,
                        18.973669290542603,
                        0.550000011920929
                    ],
                    [
                        16.366850540041924,
                        112.06046295166016,
                        19.704168558120728,
                        0.550000011920929
                    ],
                    [
                        16.557049438357353,
                        115.55146026611328,
                        20.527769327163696,
                        0.550000011920929
                    ],
                    [
                        16.674050018191338,
                        117.85246276855469,
                        21.03656792640686,
                        0.550000011920929
                    ],
                    [
                        16.719750091433525,
                        119.9434585571289,
                        21.454967737197876,
                        0.550000011920929
                    ],
                    [
                        16.834149047732353,
                        122.56246185302734,
                        21.940569162368774,
                        0.550000011920929
                    ],
                    [
                        17.070648834109306,
                        125.30046081542969,
                        22.336668252944946,
                        0.550000011920929
                    ],
                    [
                        17.513649627566338,
                        129.04046630859375,
                        22.880468606948853,
                        0.2800000011920929
                    ]
                ]
            },
            "ions": {
                "k": {
                    "e": -85.0,
                    "i": 54.4,
                    "o": 2.5
                },
                "na": {
                    "e": 50.0,
                    "i": 10.0,
                    "o": 140.0
                }
            },
            "mechs": {
                "Ih": {
                    "gIhbar": [
                        7.316032143962623e-05,
                        8.171199229417388e-05,
                        9.088143109975873e-05,
                        0.0001007132650699183,
                        0.00011680866825070564
                    ]
                },
                "Im": {
                    "gImbar": 8e-06
                },
                "K_Pst": {
                    "gK_Pstbar": 1e-05
                },
                "K_Tst": {
                    "gK_Tstbar": 0.0095
                },
                "NaTs2_t": {
                    "gNaTs2_tbar": 1e-05
                },
                "Nap_Et2": {
                    "gNap_Et2bar": 1e-06
                },
                "SKv3_1": {
                    "gSKv3_1bar": 0.004399
                },
                "pas": {
                    "e": -79.31574,
                    "g": 1e-06
                }
            },
            "topol": {
                "childX": 0.0,
                "parentSec": "dend_0",
                "parentX": 1.0
            }
        },
        "dend_10": {
            "geom": {
                "L": 39.13708164508982,
                "Ra": 100.0,
                "cm": 1.0,
                "diam": 0.4787053714201224,
                "nseg": 1,
                "pt3d": [
                    [
                        -24.2502511292696,
                        -98.95723724365234,
                        44.77096962928772,
                        0.550000011920929
                    ],
                    [
                        -29.226950958371162,
                        -105.31954193115234,
                        43.33576989173889,
                        0.550000011920929
                    ],
                    [
                        -31.425450637936592,
                        -108.03553771972656,
                        42.842968225479126,
                        0.550000011920929
                    ],
                    [
                        -36.159148529171944,
                        -113.78653717041016,
                        42.00476861000061,
                        0.550000011920929
                    ],
                    [
                        -38.226748779416084,
                        -116.24053955078125,
                        41.7296679019928,
                        0.550000011920929
                    ],
                    [
                        -40.30635006725788,
                        -118.61553955078125,
                        41.55896782875061,
                        0.2800000011920929
                    ],
                    [
                        -41.23575146496296,
                        -119.6765365600586,
                        41.482670068740845,
                        0.550000011920929
                    ],
                    [
                        -43.54764874279499,
                        -122.09954071044922,
                        41.57936882972717,
                        0.2800000011920929
                    ],
                    [
                        -45.060950592160225,
                        -123.67153930664062,
                        41.697670221328735,
                        0.550000011920929
                    ],
                    [
                        -46.87655194103718,
                        -125.49253845214844,
                        42.06456780433655,
                        0.2800000011920929
                    ],
                    [
                        -49.73525173962116,
                        -128.20054626464844,
                        42.648468255996704,
                        0.2800000011920929
                    ]
                ]
            },
            "ions": {
                "k": {
                    "e": -85.0,
                    "i": 54.4,
                    "o": 2.5
                },
                "na": {
                    "e": 50.0,
                    "i": 10.0,
                    "o": 140.0
                }
            },
            "mechs": {
                "Ih": {
                    "gIhbar": 0.00012676598625440669
                },
                "Im": {
                    "gImbar": 8e-06
                },
                "K_Pst": {
                    "gK_Pstbar": 1e-05
                },
                "K_Tst": {
                    "gK_Tstbar": 0.0095
                },
                "NaTs2_t": {
                    "gNaTs2_tbar": 1e-05
                },
                "Nap_Et2": {
                    "gNap_Et2bar": 1e-06
                },
                "SKv3_1": {
                    "gSKv3_1bar": 0.004399
                },
                "pas": {
                    "e": -79.31574,
                    "g": 1e-06
                }
            },
            "topol": {
                "childX": 0.0,
                "parentSec": "dend_9",
                "parentX": 1.0
            }
        },
        "dend_11": {
            "geom": {
                "L": 68.52671352065124,
                "Ra": 100.0,
                "cm": 1.0,
                "diam": 0.8299999833106994,
                "nseg": 3,
                "pt3d": [
                    [
                        -24.2502511292696,
                        -98.95723724365234,
                        44.77096962928772,
                        0.8299999833106995
                    ],
                    [
                        -24.278750732541084,
                        -104.26753997802734,
                        46.22366738319397,
                        0.8299999833106995
                    ],
                    [
                        -24.265250518918037,
                        -108.54154205322266,
                        47.658367395401,
                        0.8299999833106995
                    ],
                    [
                        -24.2065499573946,
                        -110.54653930664062,
                        48.32906746864319,
                        0.8299999833106995
                    ],
                    [
                        -24.168549850583076,
                        -111.70353698730469,
                        48.808269739151,
                        0.8299999833106995
                    ],
                    [
                        -24.12325032055378,
                        -114.86154174804688,
                        50.20476937294006,
                        0.8299999833106995
                    ],
                    [
                        -24.132951095700264,
                        -116.72154235839844,
                        50.91066765785217,
                        0.8299999833106995
                    ],
                    [
                        -24.185550048947334,
                        -120.24353790283203,
                        51.929569482803345,
                        0.8299999833106995
                    ],
                    [
                        -24.128650024533272,
                        -122.69654083251953,
                        52.622867822647095,
                        0.8299999833106995
                    ],
                    [
                        -23.871051147580147,
                        -126.89453887939453,
                        53.634166955947876,
                        0.8299999833106995
                    ],
                    [
                        -23.663050964474678,
                        -129.05853271484375,
                        54.00046944618225,
                        0.8299999833106995
                    ],
                    [
                        -23.12914974987507,
                        -134.36953735351562,
                        54.41006875038147,
                        0.8299999833106995
                    ],
                    [
                        -22.743050888180733,
                        -139.09153747558594,
                        54.49986672401428,
                        0.8299999833106995
                    ],
                    [
                        -22.579350784420967,
                        -142.9745330810547,
                        54.284366846084595,
                        0.8299999833106995
                    ],
                    [
                        -22.600650146603584,
                        -145.76954650878906,
                        54.08006691932678,
                        0.8299999833106995
                    ],
                    [
                        -22.616250351071358,
                        -146.33253479003906,
                        54.02366662025452,
                        0.8299999833106995
                    ],
                    [
                        -22.796050384640694,
                        -149.55453491210938,
                        53.88097023963928,
                        0.2800000011920929
                    ],
                    [
                        -22.886349990963936,
                        -150.40553283691406,
                        53.91156792640686,
                        0.8299999833106995
                    ],
                    [
                        -23.267949417233467,
                        -152.58453369140625,
                        53.96526741981506,
                        0.2800000011920929
                    ],
                    [
                        -24.005349472165108,
                        -156.44754028320312,
                        54.014068841934204,
                        0.2800000011920929
                    ],
                    [
                        -24.16644985973835,
                        -157.2765350341797,
                        54.055668115615845,
                        0.2800000011920929
                    ],
                    [
                        -24.658150985836983,
                        -159.92454528808594,
                        54.203468561172485,
                        0.8299999833106995
                    ],
                    [
                        -25.032849624753,
                        -162.2725372314453,
                        54.35246682167053,
                        0.2800000011920929
                    ],
                    [
                        -25.31734974682331,
                        -164.15853881835938,
                        54.49366784095764,
                        0.8299999833106995
                    ],
                    [
                        -25.480250671505928,
                        -165.675537109375,
                        54.63276696205139,
                        0.2800000011920929
                    ]
                ]
            },
            "ions": {
                "k": {
                    "e": -85.0,
                    "i": 54.4,
                    "o": 2.5
                },
                "na": {
                    "e": 50.0,
                    "i": 10.0,
                    "o": 140.0
                }
            },
            "mechs": {
                "Ih": {
                    "gIhbar": [
                        0.00011304413876658694,
                        0.0001242695150412709,
                        0.0001426179467389754
                    ]
                },
                "Im": {
                    "gImbar": 8e-06
                },
                "K_Pst": {
                    "gK_Pstbar": 1e-05
                },
                "K_Tst": {
                    "gK_Tstbar": 0.0095
                },
                "NaTs2_t": {
                    "gNaTs2_tbar": 1e-05
                },
                "Nap_Et2": {
                    "gNap_Et2bar": 1e-06
                },
                "SKv3_1": {
                    "gSKv3_1bar": 0.004399
                },
                "pas": {
                    "e": -79.31574,
                    "g": 1e-06
                }
            },
            "topol": {
                "childX": 0.0,
                "parentSec": "dend_9",
                "parentX": 1.0
            }
        },
        "dend_2": {
            "geom": {
                "L": 46.36488639649947,
                "Ra": 100.0,
                "cm": 1.0,
                "diam": 0.7635443098522837,
                "nseg": 3,
                "pt3d": [
                    [
                        0.7935037463903427,
                        17.032461166381836,
                        2.721168279647827,
                        0.8299999833106995
                    ],
                    [
                        0.530700758099556,
                        23.577560424804688,
                        -0.23093360662460327,
                        0.8299999833106995
                    ],
                    [
                        0.5150897651910782,
                        25.302261352539062,
                        -0.9491015672683716,
                        0.8299999833106995
                    ],
                    [
                        0.49373675882816315,
                        27.416160583496094,
                        -1.8496415615081787,
                        0.8299999833106995
                    ],
                    [
                        0.5030767768621445,
                        29.162160873413086,
                        -2.5457115173339844,
                        0.8299999833106995
                    ],
                    [
                        0.5337427705526352,
                        31.954261779785156,
                        -3.603301525115967,
                        0.8299999833106995
                    ],
                    [
                        0.6222427636384964,
                        35.605560302734375,
                        -4.911161661148071,
                        0.8299999833106995
                    ],
                    [
                        0.6702157706022263,
                        38.2011604309082,
                        -5.634821653366089,
                        0.8299999833106995
                    ],
                    [
                        0.7442107647657394,
                        41.009361267089844,
                        -6.4661314487457275,
                        0.8299999833106995
                    ],
                    [
                        0.8528327792882919,
                        43.892662048339844,
                        -7.431121587753296,
                        0.550000011920929
                    ],
                    [
                        0.8869807571172714,
                        44.80575942993164,
                        -7.741901636123657,
                        0.550000011920929
                    ],
                    [
                        0.9215057939291,
                        46.36806106567383,
                        -8.282041311264038,
                        0.550000011920929
                    ],
                    [
                        1.0391957610845566,
                        49.6297607421875,
                        -9.355041265487671,
                        0.550000011920929
                    ],
                    [
                        1.1033587902784348,
                        51.99616241455078,
                        -10.10453200340271,
                        0.550000011920929
                    ],
                    [
                        1.3103198260068893,
                        57.92616271972656,
                        -11.97733187675476,
                        0.550000011920929
                    ],
                    [
                        1.3732797354459763,
                        60.6031608581543,
                        -12.930731534957886,
                        0.550000011920929
                    ]
                ]
            },
            "ions": {
                "k": {
                    "e": -85.0,
                    "i": 54.4,
                    "o": 2.5
                },
                "na": {
                    "e": 50.0,
                    "i": 10.0,
                    "o": 140.0
                }
            },
            "mechs": {
                "Ih": {
                    "gIhbar": [
                        7.178426464110902e-05,
                        7.733685861763318e-05,
                        8.61636718946827e-05
                    ]
                },
                "Im": {
                    "gImbar": 8e-06
                },
                "K_Pst": {
                    "gK_Pstbar": 1e-05
                },
                "K_Tst": {
                    "gK_Tstbar": 0.0095
                },
                "NaTs2_t": {
                    "gNaTs2_tbar": 1e-05
                },
                "Nap_Et2": {
                    "gNap_Et2bar": 1e-06
                },
                "SKv3_1": {
                    "gSKv3_1bar": 0.004399
                },
                "pas": {
                    "e": -79.31574,
                    "g": 1e-06
                }
            },
            "topol": {
                "childX": 0.0,
                "parentSec": "dend_0",
                "parentX": 1.0
            }
        },
        "dend_3": {
            "geom": {
                "L": 57.16655687154107,
                "Ra": 100.0,
                "cm": 1.0,
                "diam": 0.6184040046126892,
                "nseg": 3,
                "pt3d": [
                    [
                        1.3732797354459763,
                        60.6031608581543,
                        -12.930731534957886,
                        0.2800000011920929
                    ],
                    [
                        1.7904997318983078,
                        64.34806060791016,
                        -16.616832494735718,
                        0.2800000011920929
                    ],
                    [
                        1.872079774737358,
                        64.90856170654297,
                        -17.148832082748413,
                        0.550000011920929
                    ],
                    [
                        2.6413797587156296,
                        69.86456298828125,
                        -21.63443160057068,
                        0.2800000011920929
                    ],
                    [
                        3.5192598551511765,
                        74.48175811767578,
                        -26.03343176841736,
                        1.1100000143051147
                    ],
                    [
                        4.066159650683403,
                        76.88046264648438,
                        -28.43593192100525,
                        0.2800000011920929
                    ],
                    [
                        4.066159650683403,
                        76.88046264648438,
                        -28.43593192100525,
                        0.550000011920929
                    ],
                    [
                        4.980849906802177,
                        79.79546356201172,
                        -30.700931310653687,
                        0.2800000011920929
                    ],
                    [
                        5.409009620547295,
                        80.91116333007812,
                        -31.430631399154663,
                        1.1100000143051147
                    ],
                    [
                        7.96885983645916,
                        85.84666442871094,
                        -33.07863211631775,
                        0.550000011920929
                    ],
                    [
                        10.3205496519804,
                        89.68156433105469,
                        -33.045032262802124,
                        0.2800000011920929
                    ],
                    [
                        14.268549606204033,
                        95.67166137695312,
                        -32.16993308067322,
                        1.1100000143051147
                    ],
                    [
                        17.751848861575127,
                        100.7474594116211,
                        -30.827831029891968,
                        0.2800000011920929
                    ],
                    [
                        17.838850662112236,
                        100.86546325683594,
                        -30.768232107162476,
                        0.550000011920929
                    ],
                    [
                        20.43924967944622,
                        104.199462890625,
                        -28.389732122421265,
                        0.2800000011920929
                    ],
                    [
                        20.671349212527275,
                        104.49246215820312,
                        -28.0966317653656,
                        0.550000011920929
                    ]
                ]
            },
            "ions": {
                "k": {
                    "e": -85.0,
                    "i": 54.4,
                    "o": 2.5
                },
                "na": {
                    "e": 50.0,
                    "i": 10.0,
                    "o": 140.0
                }
            },
            "mechs": {
                "Ih": {
                    "gIhbar": [
                        8.997322672286105e-05,
                        9.792687990987418e-05,
                        0.00011074310550542485
                    ]
                },
                "Im": {
                    "gImbar": 8e-06
                },
                "K_Pst": {
                    "gK_Pstbar": 1e-05
                },
                "K_Tst": {
                    "gK_Tstbar": 0.0095
                },
                "NaTs2_t": {
                    "gNaTs2_tbar": 1e-05
                },
                "Nap_Et2": {
                    "gNap_Et2bar": 1e-06
                },
                "SKv3_1": {
                    "gSKv3_1bar": 0.004399
                },
                "pas": {
                    "e": -79.31574,
                    "g": 1e-06
                }
            },
            "topol": {
                "childX": 0.0,
                "parentSec": "dend_2",
                "parentX": 1.0
            }
        },
        "dend_4": {
            "geom": {
                "L": 37.179835514022244,
                "Ra": 100.0,
                "cm": 1.0,
                "diam": 0.7077019483893678,
                "nseg": 1,
                "pt3d": [
                    [
                        1.3732797354459763,
                        60.6031608581543,
                        -12.930731534957886,
                        0.550000011920929
                    ],
                    [
                        1.931919738650322,
                        63.859859466552734,
                        -13.16193175315857,
                        0.550000011920929
                    ],
                    [
                        2.5352298468351364,
                        67.29995727539062,
                        -13.497231245040894,
                        0.550000011920929
                    ],
                    [
                        2.958509847521782,
                        69.7183609008789,
                        -13.709831953048706,
                        0.550000011920929
                    ],
                    [
                        3.6282197684049606,
                        73.34686279296875,
                        -14.006232023239136,
                        0.8299999833106995
                    ],
                    [
                        4.104769870638847,
                        75.92616271972656,
                        -14.202231168746948,
                        0.550000011920929
                    ],
                    [
                        4.571839973330498,
                        78.33016204833984,
                        -14.372331380844116,
                        0.550000011920929
                    ],
                    [
                        5.005319759249687,
                        80.57936096191406,
                        -14.468931913375854,
                        1.1100000143051147
                    ],
                    [
                        5.7932397574186325,
                        84.48326110839844,
                        -14.748231649398804,
                        0.550000011920929
                    ],
                    [
                        6.024089977145195,
                        85.79066467285156,
                        -14.869831800460815,
                        0.550000011920929
                    ],
                    [
                        6.3100597113370895,
                        87.44026184082031,
                        -15.042131185531616,
                        1.1100000143051147
                    ],
                    [
                        6.655859634280205,
                        89.48766326904297,
                        -15.271631956100464,
                        0.550000011920929
                    ],
                    [
                        6.857139751315117,
                        90.82666015625,
                        -15.42483115196228,
                        1.1100000143051147
                    ],
                    [
                        7.4292799681425095,
                        94.91555786132812,
                        -15.85513186454773,
                        0.550000011920929
                    ],
                    [
                        7.668459579348564,
                        97.07295989990234,
                        -16.23503088951111,
                        1.1100000143051147
                    ]
                ]
            },
            "ions": {
                "k": {
                    "e": -85.0,
                    "i": 54.4,
                    "o": 2.5
                },
                "na": {
                    "e": 50.0,
                    "i": 10.0,
                    "o": 140.0
                }
            },
            "mechs": {
                "Ih": {
                    "gIhbar": 0.00010166673698084216
                },
                "Im": {
                    "gImbar": 8e-06
                },
                "K_Pst": {
                    "gK_Pstbar": 1e-05
                },
                "K_Tst": {
                    "gK_Tstbar": 0.0095
                },
                "NaTs2_t": {
                    "gNaTs2_tbar": 1e-05
                },
                "Nap_Et2": {
                    "gNap_Et2bar": 1e-06
                },
                "SKv3_1": {
                    "gSKv3_1bar": 0.004399
                },
                "pas": {
                    "e": -79.31574,
                    "g": 1e-06
                }
            },
            "topol": {
                "childX": 0.0,
                "parentSec": "dend_2",
                "parentX": 1.0
            }
        },
        "dend_5": {
            "geom": {
                "L": 49.662315033615016,
                "Ra": 100.0,
                "cm": 1.0,
                "diam": 1.2690271562382074,
                "nseg": 3,
                "pt3d": [
                    [
                        0.10894936695694923,
                        -8.91365909576416,
                        10.785167932510376,
                        1.659999966621399
                    ],
                    [
                        -0.5461502224206924,
                        -11.603439331054688,
                        12.907768487930298,
                        1.659999966621399
                    ],
                    [
                        -1.2532202750444412,
                        -14.506738662719727,
                        15.198868036270142,
                        1.659999966621399
                    ],
                    [
                        -2.4675303250551224,
                        -19.492639541625977,
                        19.133367776870728,
                        1.3899999856948853
                    ],
                    [
                        -7.2968199998140335,
                        -39.32154083251953,
                        34.781170129776,
                        1.1100000143051147
                    ],
                    [
                        -8.143989875912666,
                        -42.8000373840332,
                        37.52616906166077,
                        1.1100000143051147
                    ],
                    [
                        -9.21696026623249,
                        -47.20563888549805,
                        41.00266671180725,
                        1.1100000143051147
                    ]
                ]
            },
            "ions": {
                "k": {
                    "e": -85.0,
                    "i": 54.4,
                    "o": 2.5
                },
                "na": {
                    "e": 50.0,
                    "i": 10.0,
                    "o": 140.0
                }
            },
            "mechs": {
                "Ih": {
                    "gIhbar": [
                        6.885328123618197e-05,
                        7.46614118964177e-05,
                        8.393275368421575e-05
                    ]
                },
                "Im": {
                    "gImbar": 8e-06
                },
                "K_Pst": {
                    "gK_Pstbar": 1e-05
                },
                "K_Tst": {
                    "gK_Tstbar": 0.0095
                },
                "NaTs2_t": {
                    "gNaTs2_tbar": 1e-05
                },
                "Nap_Et2": {
                    "gNap_Et2bar": 1e-06
                },
                "SKv3_1": {
                    "gSKv3_1bar": 0.004399
                },
                "pas": {
                    "e": -79.31574,
                    "g": 1e-06
                }
            },
            "topol": {
                "childX": 0.0,
                "parentSec": "soma",
                "parentX": 0.5
            }
        },
        "dend_6": {
            "geom": {
                "L": 132.82861084888802,
                "Ra": 100.0,
                "cm": 1.0,
                "diam": 0.5500000119209291,
                "nseg": 7,
                "pt3d": [
                    [
                        -9.21696026623249,
                        -47.20563888549805,
                        41.00266671180725,
                        0.8299999833106995
                    ],
                    [
                        -9.211739853024483,
                        -49.26573944091797,
                        41.32426857948303,
                        0.8299999833106995
                    ],
                    [
                        -9.207080200314522,
                        -51.131839752197266,
                        41.588268518447876,
                        0.8299999833106995
                    ],
                    [
                        -9.277230575680733,
                        -53.578338623046875,
                        41.90216851234436,
                        0.8299999833106995
                    ],
                    [
                        -9.340990379452705,
                        -59.16923904418945,
                        42.4785692691803,
                        0.8299999833106995
                    ],
                    [
                        -9.33387978374958,
                        -63.782737731933594,
                        42.88826775550842,
                        0.550000011920929
                    ],
                    [
                        -9.321530655026436,
                        -71.60923767089844,
                        43.41896843910217,
                        0.550000011920929
                    ],
                    [
                        -9.210720375180244,
                        -75.49874114990234,
                        43.71727013587952,
                        0.8299999833106995
                    ],
                    [
                        -8.986240699887276,
                        -79.94413757324219,
                        44.06496834754944,
                        0.550000011920929
                    ],
                    [
                        -8.415520027279854,
                        -87.19883728027344,
                        44.84376931190491,
                        0.550000011920929
                    ],
                    [
                        -8.212060287594795,
                        -89.26943969726562,
                        45.09116768836975,
                        0.550000011920929
                    ],
                    [
                        -7.643710449337959,
                        -94.88323974609375,
                        45.79286980628967,
                        0.550000011920929
                    ],
                    [
                        -6.906470134854317,
                        -101.95954132080078,
                        46.84996819496155,
                        0.550000011920929
                    ],
                    [
                        -6.470510318875313,
                        -106.19554138183594,
                        47.529369592666626,
                        0.550000011920929
                    ],
                    [
                        -5.942930057644844,
                        -111.83753967285156,
                        48.48366951942444,
                        0.550000011920929
                    ],
                    [
                        -5.337300136685371,
                        -122.0045394897461,
                        50.30386757850647,
                        0.550000011920929
                    ],
                    [
                        -5.166470363736153,
                        -127.37654113769531,
                        51.24326729774475,
                        0.550000011920929
                    ],
                    [
                        -5.122580364346504,
                        -131.38853454589844,
                        51.88876748085022,
                        0.550000011920929
                    ],
                    [
                        -5.25287039577961,
                        -134.1775360107422,
                        52.2213671207428,
                        0.550000011920929
                    ],
                    [
                        -5.489500358700752,
                        -136.62254333496094,
                        52.46266961097717,
                        0.550000011920929
                    ],
                    [
                        -6.168930366635323,
                        -141.53053283691406,
                        53.04686760902405,
                        0.550000011920929
                    ],
                    [
                        -6.563530281186104,
                        -143.98753356933594,
                        53.35866951942444,
                        0.550000011920929
                    ],
                    [
                        -7.186640098690987,
                        -147.73753356933594,
                        53.987468957901,
                        0.550000011920929
                    ],
                    [
                        -8.038629844784737,
                        -152.758544921875,
                        54.91026711463928,
                        0.550000011920929
                    ],
                    [
                        -9.353730514645576,
                        -160.00253295898438,
                        56.347870111465454,
                        0.550000011920929
                    ],
                    [
                        -10.499249771237373,
                        -166.52154541015625,
                        57.73576760292053,
                        0.550000011920929
                    ],
                    [
                        -11.550850227475166,
                        -172.20654296875,
                        59.061866998672485,
                        0.8299999833106995
                    ],
                    [
                        -12.572250679135323,
                        -177.6315460205078,
                        60.512768030166626,
                        0.8299999833106995
                    ]
                ]
            },
            "ions": {
                "k": {
                    "e": -85.0,
                    "i": 54.4,
                    "o": 2.5
                },
                "na": {
                    "e": 50.0,
                    "i": 10.0,
                    "o": 140.0
                }
            },
            "mechs": {
                "Ih": {
                    "gIhbar": [
                        8.76616745355163e-05,
                        9.544557067685261e-05,
                        0.00010368547657373213,
                        0.00011240777858311355,
                        0.00012164150234901775,
                        0.0001314156039613668,
                        0.0001471615241104527
                    ]
                },
                "Im": {
                    "gImbar": 8e-06
                },
                "K_Pst": {
                    "gK_Pstbar": 1e-05
                },
                "K_Tst": {
                    "gK_Tstbar": 0.0095
                },
                "NaTs2_t": {
                    "gNaTs2_tbar": 1e-05
                },
                "Nap_Et2": {
                    "gNap_Et2bar": 1e-06
                },
                "SKv3_1": {
                    "gSKv3_1bar": 0.004399
                },
                "pas": {
                    "e": -79.31574,
                    "g": 1e-06
                }
            },
            "topol": {
                "childX": 0.0,
                "parentSec": "dend_5",
                "parentX": 1.0
            }
        },
        "dend_7": {
            "geom": {
                "L": 18.837338474783643,
                "Ra": 100.0,
                "cm": 1.0,
                "diam": 0.8299999833106995,
                "nseg": 1,
                "pt3d": [
                    [
                        -9.21696026623249,
                        -47.20563888549805,
                        41.00266671180725,
                        0.8299999833106995
                    ],
                    [
                        -10.652650192379951,
                        -53.66353988647461,
                        38.822269678115845,
                        0.8299999833106995
                    ],
                    [
                        -10.9944499284029,
                        -55.20124053955078,
                        38.30306649208069,
                        0.8299999833106995
                    ],
                    [
                        -11.867050483822823,
                        -59.126338958740234,
                        36.97776818275452,
                        0.8299999833106995
                    ],
                    [
                        -12.258250549435616,
                        -60.88583755493164,
                        36.38366723060608,
                        0.8299999833106995
                    ],
                    [
                        -13.099450424313545,
                        -64.66993713378906,
                        35.10606789588928,
                        0.8299999833106995
                    ]
                ]
            },
            "ions": {
                "k": {
                    "e": -85.0,
                    "i": 54.4,
                    "o": 2.5
                },
                "na": {
                    "e": 50.0,
                    "i": 10.0,
                    "o": 140.0
                }
            },
            "mechs": {
                "Ih": {
                    "gIhbar": 9.144158679814348e-05
                },
                "Im": {
                    "gImbar": 8e-06
                },
                "K_Pst": {
                    "gK_Pstbar": 1e-05
                },
                "K_Tst": {
                    "gK_Tstbar": 0.0095
                },
                "NaTs2_t": {
                    "gNaTs2_tbar": 1e-05
                },
                "Nap_Et2": {
                    "gNap_Et2bar": 1e-06
                },
                "SKv3_1": {
                    "gSKv3_1bar": 0.004399
                },
                "pas": {
                    "e": -79.31574,
                    "g": 1e-06
                }
            },
            "topol": {
                "childX": 0.0,
                "parentSec": "dend_5",
                "parentX": 1.0
            }
        },
        "dend_8": {
            "geom": {
                "L": 30.57619197159506,
                "Ra": 100.0,
                "cm": 1.0,
                "diam": 0.5250048041818288,
                "nseg": 1,
                "pt3d": [
                    [
                        -13.099450424313545,
                        -64.66993713378906,
                        35.10606789588928,
                        0.550000011920929
                    ],
                    [
                        -14.106650665402412,
                        -64.34004211425781,
                        42.47316765785217,
                        0.550000011920929
                    ],
                    [
                        -14.967649772763252,
                        -63.891136169433594,
                        50.38246941566467,
                        0.550000011920929
                    ],
                    [
                        -15.404950454831123,
                        -63.66313934326172,
                        54.40016961097717,
                        0.550000011920929
                    ],
                    [
                        -15.955849960446358,
                        -63.375938415527344,
                        59.46056771278381,
                        0.2800000011920929
                    ],
                    [
                        -16.046849563717842,
                        -63.32854080200195,
                        60.29657006263733,
                        0.8299999833106995
                    ],
                    [
                        -16.524249389767647,
                        -63.07963943481445,
                        64.68206810951233,
                        0.2800000011920929
                    ],
                    [
                        -16.590350463986397,
                        -62.98283767700195,
                        65.43056511878967,
                        0.550000011920929
                    ]
                ]
            },
            "ions": {
                "k": {
                    "e": -85.0,
                    "i": 54.4,
                    "o": 2.5
                },
                "na": {
                    "e": 50.0,
                    "i": 10.0,
                    "o": 140.0
                }
            },
            "mechs": {
                "Ih": {
                    "gIhbar": 0.00010457035564800446
                },
                "Im": {
                    "gImbar": 8e-06
                },
                "K_Pst": {
                    "gK_Pstbar": 1e-05
                },
                "K_Tst": {
                    "gK_Tstbar": 0.0095
                },
                "NaTs2_t": {
                    "gNaTs2_tbar": 1e-05
                },
                "Nap_Et2": {
                    "gNap_Et2bar": 1e-06
                },
                "SKv3_1": {
                    "gSKv3_1bar": 0.004399
                },
                "pas": {
                    "e": -79.31574,
                    "g": 1e-06
                }
            },
            "topol": {
                "childX": 0.0,
                "parentSec": "dend_7",
                "parentX": 1.0
            }
        },
        "dend_9": {
            "geom": {
                "L": 37.49806563729826,
                "Ra": 100.0,
                "cm": 1.0,
                "diam": 0.8299999833106995,
                "nseg": 1,
                "pt3d": [
                    [
                        -13.099450424313545,
                        -64.66993713378906,
                        35.10606789588928,
                        0.8299999833106995
                    ],
                    [
                        -14.97834999859333,
                        -70.3244400024414,
                        37.407169580459595,
                        0.8299999833106995
                    ],
                    [
                        -16.46365101635456,
                        -74.7995376586914,
                        39.02206826210022,
                        0.8299999833106995
                    ],
                    [
                        -18.25175030529499,
                        -80.19063568115234,
                        40.74126839637756,
                        0.8299999833106995
                    ],
                    [
                        -19.74665005505085,
                        -84.64163970947266,
                        42.01796746253967,
                        0.8299999833106995
                    ],
                    [
                        -20.65515072643757,
                        -87.34664154052734,
                        42.79386925697327,
                        0.8299999833106995
                    ],
                    [
                        -21.738351181149483,
                        -90.57173919677734,
                        43.71886849403381,
                        0.8299999833106995
                    ],
                    [
                        -22.44675000011921,
                        -92.9056396484375,
                        44.221168756484985,
                        0.8299999833106995
                    ],
                    [
                        -23.255650833249092,
                        -95.56663513183594,
                        44.68016839027405,
                        0.8299999833106995
                    ],
                    [
                        -24.2502511292696,
                        -98.95723724365234,
                        44.77096962928772,
                        0.8299999833106995
                    ]
                ]
            },
            "ions": {
                "k": {
                    "e": -85.0,
                    "i": 54.4,
                    "o": 2.5
                },
                "na": {
                    "e": 50.0,
                    "i": 10.0,
                    "o": 140.0
                }
            },
            "mechs": {
                "Ih": {
                    "gIhbar": 0.00010771340691539518
                },
                "Im": {
                    "gImbar": 8e-06
                },
                "K_Pst": {
                    "gK_Pstbar": 1e-05
                },
                "K_Tst": {
                    "gK_Tstbar": 0.0095
                },
                "NaTs2_t": {
                    "gNaTs2_tbar": 1e-05
                },
                "Nap_Et2": {
                    "gNap_Et2bar": 1e-06
                },
                "SKv3_1": {
                    "gSKv3_1bar": 0.004399
                },
                "pas": {
                    "e": -79.31574,
                    "g": 1e-06
                }
            },
            "topol": {
                "childX": 0.0,
                "parentSec": "dend_7",
                "parentX": 1.0
            }
        },
        "soma": {
            "geom": {
                "L": 16.68760059105284,
                "Ra": 100.0,
                "cm": 1.0,
                "diam": 6.183955039804921,
                "nseg": 1,
                "pt3d": [
                    [
                        -0.39067913591861725,
                        -8.309144973754883,
                        -0.6515205502510071,
                        1.8951969146728516
                    ],
                    [
                        -0.3516112118959427,
                        -7.4782304763793945,
                        -0.5863685011863708,
                        3.082066297531128
                    ],
                    [
                        -0.3125433176755905,
                        -6.6473164558410645,
                        -0.5212163925170898,
                        4.072286605834961
                    ],
                    [
                        -0.27347539365291595,
                        -5.816401958465576,
                        -0.4560643434524536,
                        5.062507152557373
                    ],
                    [
                        -0.23440749943256378,
                        -4.98548698425293,
                        -0.39091232419013977,
                        6.037050247192383
                    ],
                    [
                        -0.19533957540988922,
                        -4.154572486877441,
                        -0.32576024532318115,
                        6.871528625488281
                    ],
                    [
                        -0.15627165138721466,
                        -3.3236582279205322,
                        -0.2606081962585449,
                        7.336226463317871
                    ],
                    [
                        -0.1172037273645401,
                        -2.492743730545044,
                        -0.1954561471939087,
                        7.772766590118408
                    ],
                    [
                        -0.07813583314418793,
                        -1.6618289947509766,
                        -0.13030411303043365,
                        8.204809188842773
                    ],
                    [
                        -0.03906790912151337,
                        -0.8309144973754883,
                        -0.06515204906463623,
                        8.513321876525879
                    ],
                    [
                        0.0,
                        0.0,
                        0.0,
                        8.819425582885742
                    ],
                    [
                        0.03906792402267456,
                        0.8309145122766495,
                        0.0651520537212491,
                        9.101800918579102
                    ],
                    [
                        0.07813582569360733,
                        1.6618291139602661,
                        0.13030410557985306,
                        8.766189575195312
                    ],
                    [
                        0.1172037422657013,
                        2.4927436113357544,
                        0.19545616209506989,
                        8.180747985839844
                    ],
                    [
                        0.15627165604382753,
                        3.323657989501953,
                        0.2606082111597061,
                        7.291065216064453
                    ],
                    [
                        0.19533957168459892,
                        4.1545727252960205,
                        0.32576027512550354,
                        6.470125675201416
                    ],
                    [
                        0.2344074845314026,
                        4.98548698425293,
                        0.39091232419013977,
                        5.692709445953369
                    ],
                    [
                        0.27347540110349655,
                        5.816401481628418,
                        0.456064373254776,
                        4.7843499183654785
                    ],
                    [
                        0.3125433176755905,
                        6.647315979003906,
                        0.5212164223194122,
                        3.7614963054656982
                    ],
                    [
                        0.3516112267971039,
                        7.478230953216553,
                        0.5863685011863708,
                        2.1628196239471436
                    ],
                    [
                        0.39067913591861725,
                        8.309145450592041,
                        0.6515205502510071,
                        1.4964182376861572
                    ]
                ]
            },
            "ions": {
                "ca": {
                    "e": 132.4579341637009,
                    "i": 5e-05,
                    "o": 2.0
                },
                "k": {
                    "e": -85.0,
                    "i": 54.4,
                    "o": 2.5
                },
                "na": {
                    "e": 50.0,
                    "i": 10.0,
                    "o": 140.0
                }
            },
            "mechs": {
                "Ca": {
                    "gCabar": 3.2e-05
                },
                "CaDynamics_E2": {
                    "decay": 731.707637,
                    "depth": 0.1,
                    "gamma": 0.000511,
                    "minCai": 0.0001
                },
                "Ca_LVAst": {
                    "gCa_LVAstbar": 0.001067
                },
                "Im": {
                    "gImbar": 8e-06
                },
                "K_Pst": {
                    "gK_Pstbar": 0.156376
                },
                "K_Tst": {
                    "gK_Tstbar": 0.092965
                },
                "NaTs2_t": {
                    "gNaTs2_tbar": 0.197999
                },
                "Nap_Et2": {
                    "gNap_Et2bar": 1e-06
                },
                "SK_E2": {
                    "gSK_E2bar": 0.019726
                },
                "SKv3_1": {
                    "gSKv3_1bar": 0.297559
                },
                "pas": {
                    "e": -62.442793,
                    "g": 9.1e-05
                }
            },
            "topol": {}
        }
    }
}