{
    "netpyne_changeset": "",
    "netpyne_version": "0.9.8",
    "simData": {
        "V_soma": {},
        "spkid": [
            290.0,
            25730.0,
            610.0,
            26370.0,
            26530.0,
            13090.0,
            4610.0,
            13090.0,
            22850.0,
            22690.0,
            23330.0,
            25410.0,
            26370.0,
            29730.0,
            29890.0,
            23010.0,
            30210.0,
            25250.0,
            24930.0,
            26530.0,
            26850.0,
            26690.0,
            25730.0,
            20450.0,
            20290.0,
            24770.0,
            23170.0,
            20130.0,
            25570.0,
            24130.0,
            29570.0,
            25090.0,
            27490.0,
            19970.0,
            25890.0,
            27010.0,
            24450.0,
            12610.0,
            29410.0,
            30050.0,
            610.0,
            610.0,
            25090.0,
            25090.0,
            610.0,
            610.0,
            610.0,
            610.0,
            610.0,
            610.0,
            610.0,
            23330.0,
            25090.0,
            23330.0,
            23330.0,
            610.0,
            23330.0,
            610.0,
            29730.0,
            23010.0,
            29730.0,
            610.0,
            23010.0,
            29730.0,
            23010.0,
            29730.0,
            20450.0,
            23330.0,
            23330.0,
            23330.0,
            20450.0,
            26690.0,
            23010.0,
            23010.0,
            23010.0,
            23010.0,
            23330.0,
            23330.0,
            25090.0,
            26370.0,
            23170.0,
            13410.0,
            27010.0,
            27010.0,
            27010.0,
            13410.0,
            29090.0,
            22690.0,
            22690.0,
            25090.0,
            23170.0,
            23170.0,
            23170.0,
            19970.0,
            26690.0,
            23170.0,
            29890.0,
            22690.0,
            23170.0,
            23010.0,
            25090.0,
            29890.0,
            23170.0,
            29890.0,
            23010.0,
            23170.0,
            25090.0,
            23170.0,
            23010.0,
            24770.0,
            25090.0,
            29890.0,
            13410.0,
            23010.0,
            26850.0,
            29890.0,
            23010.0,
            24770.0,
            19970.0,
            10050.0,
            24770.0,
            24770.0,
            25090.0,
            10050.0,
            23010.0,
            24770.0,
            12610.0,
            29890.0,
            25090.0,
            23010.0,
            24770.0,
            12610.0,
            10050.0,
            29890.0,
            23010.0,
            29890.0,
            29890.0,
            23010.0,
            23010.0,
            30370.0,
            23010.0,
            12610.0,
            23330.0,
            23010.0,
            12610.0,
            10050.0,
            23330.0,
            25090.0,
            23330.0,
            25090.0,
            10050.0,
            27010.0,
            23170.0,
            23330.0,
            29890.0,
            23170.0,
            25090.0,
            25090.0,
            25090.0,
            25090.0,
            23170.0,
            23170.0,
            25090.0,
            23010.0,
            23170.0,
            12610.0,
            23330.0,
            23170.0,
            23330.0,
            23330.0,
            23170.0,
            12610.0,
            25410.0,
            23170.0,
            23330.0,
            23330.0,
            23170.0,
            23330.0,
            25090.0,
            23330.0,
            23330.0,
            12610.0,
            26850.0,
            29890.0,
            25090.0,
            23330.0,
            10050.0,
            25090.0,
            29890.0,
            23330.0,
            29890.0,
            23330.0,
            24770.0,
            10050.0,
            23330.0,
            25090.0,
            23010.0,
            21890.0,
            23330.0,
            29890.0,
            24770.0,
            23330.0,
            25090.0,
            23330.0,
            23330.0,
            23330.0,
            10050.0,
            23010.0,
            23330.0,
            23010.0,
            11010.0,
            23010.0,
            21890.0,
            25410.0,
            23010.0,
            23330.0,
            23010.0,
            25410.0,
            25410.0,
            25410.0,
            29890.0,
            22690.0,
            22690.0,
            22690.0,
            25090.0,
            29890.0,
            25410.0,
            22690.0,
            25410.0,
            26690.0,
            1890.0,
            25090.0,
            29890.0,
            25090.0,
            29730.0,
            30210.0,
            29730.0,
            26690.0,
            29890.0,
            30210.0,
            29890.0,
            30210.0,
            22690.0,
            29890.0,
            29890.0,
            22690.0,
            26690.0,
            29890.0,
            12610.0,
            29890.0,
            1570.0,
            22690.0,
            29890.0,
            29890.0,
            12610.0,
            22690.0,
            29890.0,
            29410.0,
            29890.0,
            29890.0,
            22690.0,
            29890.0,
            29890.0,
            12610.0,
            22690.0,
            29890.0,
            12610.0,
            29890.0,
            610.0,
            1570.0,
            12610.0,
            1410.0,
            15650.0,
            22690.0,
            1890.0,
            22690.0,
            25090.0,
            30210.0,
            22690.0,
            24770.0,
            30210.0,
            25410.0,
            12930.0,
            24930.0,
            22690.0,
            23170.0,
            1890.0,
            27010.0,
            24770.0,
            23170.0,
            29410.0,
            12930.0,
            23170.0,
            22690.0,
            22690.0,
            12930.0,
            23170.0,
            23010.0,
            25410.0,
            29890.0,
            22690.0,
            24770.0,
            12930.0,
            29890.0,
            22690.0,
            24770.0,
            12930.0,
            1890.0,
            22690.0,
            23170.0,
            24930.0,
            12610.0,
            12930.0,
            1570.0,
            23170.0,
            23170.0,
            24770.0,
            12610.0,
            12930.0,
            29890.0,
            23170.0,
            22690.0,
            12930.0,
            22690.0,
            24770.0,
            22690.0,
            22690.0,
            29730.0,
            24770.0,
            12930.0,
            1890.0,
            29730.0,
            29730.0,
            12930.0,
            27010.0,
            12930.0,
            23170.0,
            12930.0,
            29890.0,
            29730.0,
            12930.0,
            29730.0,
            23170.0,
            26850.0,
            1890.0,
            4130.0,
            23170.0,
            24770.0,
            12930.0,
            12930.0,
            23170.0,
            22690.0,
            29730.0,
            22690.0,
            12930.0,
            29730.0,
            25410.0,
            22690.0,
            23170.0,
            29730.0,
            12930.0,
            29890.0,
            22690.0,
            15650.0,
            23170.0,
            25410.0,
            29730.0,
            12930.0,
            22690.0,
            23170.0,
            29730.0,
            12930.0,
            23170.0,
            29890.0,
            12930.0,
            1890.0,
            23170.0,
            12930.0,
            12930.0,
            12930.0,
            29730.0,
            29890.0,
            29730.0,
            15650.0,
            12930.0,
            29890.0,
            25410.0,
            12930.0,
            19970.0,
            1890.0,
            19970.0,
            19970.0,
            20450.0,
            20450.0,
            12930.0,
            20450.0,
            12930.0,
            20450.0,
            11010.0,
            12930.0,
            20450.0,
            12930.0,
            26690.0,
            12930.0,
            20450.0,
            12930.0,
            29730.0,
            25890.0,
            15650.0,
            26850.0,
            12930.0,
            20450.0,
            12930.0,
            26850.0,
            12930.0,
            12930.0,
            1890.0,
            25410.0,
            29890.0,
            12930.0,
            23010.0,
            12930.0,
            15650.0,
            27010.0,
            23170.0,
            29890.0,
            12930.0,
            15650.0,
            11010.0,
            12930.0,
            23170.0,
            12930.0,
            15650.0,
            1410.0,
            15650.0,
            1890.0,
            23170.0,
            15650.0,
            26850.0
        ],
        "spkt": [
            114.25000000010886,
            117.40000000010957,
            117.9500000001097,
            121.75000000011056,
            123.15000000011088,
            128.55000000011208,
            140.85000000011487,
            144.15000000011563,
            145.750000000116,
            146.35000000011613,
            146.40000000011614,
            146.90000000011625,
            146.90000000011625,
            146.95000000011626,
            147.00000000011627,
            147.05000000011628,
            147.05000000011628,
            147.1500000001163,
            147.35000000011635,
            147.35000000011635,
            147.35000000011635,
            147.40000000011636,
            147.6000000001164,
            147.70000000011643,
            147.75000000011644,
            147.90000000011648,
            147.9500000001165,
            148.0000000001165,
            148.0000000001165,
            148.15000000011653,
            148.20000000011655,
            148.25000000011656,
            148.55000000011663,
            148.65000000011665,
            148.70000000011666,
            148.70000000011666,
            148.75000000011667,
            148.80000000011668,
            148.95000000011672,
            149.25000000011678,
            149.40000000011682,
            158.75000000011894,
            168.95000000012126,
            169.80000000012146,
            170.20000000012155,
            180.80000000012396,
            192.8500000001267,
            203.75000000012918,
            216.30000000013203,
            229.00000000013492,
            241.95000000013786,
            242.1500000001379,
            247.65000000013916,
            249.05000000013948,
            249.1500000001395,
            251.50000000014003,
            255.3500000001409,
            265.7000000001322,
            272.4000000001261,
            279.2000000001199,
            280.70000000011856,
            280.8500000001184,
            283.15000000011634,
            288.85000000011115,
            299.0500000001019,
            299.5500000001014,
            323.50000000007964,
            326.90000000007655,
            332.60000000007136,
            336.70000000006763,
            342.20000000006263,
            347.9500000000574,
            358.00000000004826,
            359.2500000000471,
            360.6000000000459,
            360.85000000004567,
            384.60000000002407,
            384.8000000000239,
            405.95000000000465,
            411.00000000000006,
            413.4999999999978,
            423.44999999998873,
            430.69999999998214,
            460.7499999999548,
            464.7999999999511,
            480.29999999993703,
            530.999999999891,
            531.4999999998905,
            539.4999999998832,
            547.8499999998756,
            556.7999999998675,
            571.0999999998545,
            581.8499999998447,
            595.799999999832,
            596.6499999998313,
            609.6999999998194,
            617.9999999998118,
            619.4999999998105,
            619.99999999981,
            620.8999999998092,
            621.5499999998086,
            625.1499999998053,
            630.3999999998006,
            633.5999999997977,
            636.9999999997946,
            638.749999999793,
            640.2499999997916,
            642.7499999997893,
            645.6499999997867,
            649.0499999997836,
            654.7999999997784,
            661.3499999997724,
            661.849999999772,
            664.3499999997697,
            667.5499999997668,
            675.2999999997597,
            677.7999999997575,
            690.349999999746,
            715.5999999997231,
            720.7999999997184,
            724.0999999997154,
            735.3999999997051,
            740.9499999997,
            743.9999999996973,
            744.5499999996968,
            746.449999999695,
            764.3499999996787,
            765.0999999996781,
            765.4999999996777,
            768.8999999996746,
            769.0499999996745,
            771.9499999996718,
            775.4999999996686,
            803.2999999996433,
            811.4499999996359,
            815.4499999996323,
            821.8499999996264,
            830.1999999996189,
            836.8499999996128,
            838.7499999996111,
            858.7499999995929,
            860.6499999995912,
            869.7999999995828,
            870.3999999995823,
            870.9999999995817,
            872.8499999995801,
            873.7499999995792,
            883.0999999995707,
            893.3999999995614,
            893.4499999995613,
            898.9499999995563,
            899.6499999995557,
            902.4999999995531,
            905.4499999995504,
            906.4999999995495,
            912.2499999995442,
            912.449999999544,
            919.8999999995373,
            920.5999999995366,
            920.8999999995364,
            924.2999999995333,
            931.8999999995264,
            933.1999999995252,
            934.1499999995243,
            935.2999999995233,
            955.2499999995051,
            956.7499999995038,
            959.0999999995016,
            960.2499999995006,
            968.4999999994931,
            971.1499999994907,
            971.9999999994899,
            980.3499999994823,
            984.4999999994785,
            987.4499999994758,
            996.099999999468,
            998.4499999994658,
            1000.0499999994644,
            1003.799999999461,
            1005.7499999994592,
            1008.9999999994562,
            1021.6499999994447,
            1023.0499999994435,
            1025.3499999994474,
            1026.1499999994503,
            1029.3999999994621,
            1030.8999999994676,
            1031.5999999994701,
            1034.9999999994825,
            1036.1499999994867,
            1041.3499999995056,
            1041.4999999995061,
            1044.2999999995163,
            1046.0499999995227,
            1050.1499999995376,
            1051.2999999995418,
            1051.3999999995422,
            1052.449999999546,
            1054.349999999553,
            1055.0499999995554,
            1057.3499999995638,
            1061.0999999995774,
            1068.099999999603,
            1069.2999999996073,
            1080.2499999996471,
            1084.1999999996615,
            1087.1499999996722,
            1090.3499999996839,
            1091.3999999996877,
            1100.1999999997197,
            1102.9499999997297,
            1111.3999999997604,
            1121.449999999797,
            1122.1499999997995,
            1122.6499999998014,
            1123.7999999998056,
            1132.5999999998376,
            1132.5999999998376,
            1143.1999999998761,
            1149.499999999899,
            1157.7999999999292,
            1164.849999999955,
            1170.099999999974,
            1172.2499999999818,
            1178.7000000000053,
            1190.3500000000477,
            1196.2500000000691,
            1198.150000000076,
            1202.00000000009,
            1205.4000000001024,
            1208.600000000114,
            1234.9000000002097,
            1241.1500000002325,
            1247.7000000002563,
            1250.2000000002654,
            1257.0500000002903,
            1260.000000000301,
            1263.000000000312,
            1264.9000000003189,
            1271.8500000003442,
            1276.8000000003622,
            1276.9500000003627,
            1278.5500000003685,
            1280.1000000003742,
            1284.6500000003907,
            1286.8500000003987,
            1289.700000000409,
            1299.1500000004435,
            1301.0500000004504,
            1305.350000000466,
            1325.3000000005386,
            1330.5000000005575,
            1330.7500000005584,
            1344.350000000608,
            1355.2500000006476,
            1357.5000000006557,
            1358.950000000661,
            1361.40000000067,
            1369.0000000006976,
            1373.800000000715,
            1378.4000000007318,
            1378.750000000733,
            1390.250000000775,
            1391.2500000007785,
            1401.9000000008173,
            1406.500000000834,
            1419.3500000008808,
            1421.350000000888,
            1433.0500000009306,
            1455.2000000010112,
            1455.6500000010128,
            1461.1500000010328,
            1466.3000000010516,
            1470.300000001066,
            1483.2500000011132,
            1496.3000000011607,
            1496.400000001161,
            1504.1500000011893,
            1508.4000000012047,
            1510.400000001212,
            1510.400000001212,
            1511.7000000012167,
            1515.600000001231,
            1519.6500000012456,
            1521.150000001251,
            1534.050000001298,
            1536.0000000013051,
            1536.3000000013062,
            1538.9000000013157,
            1539.250000001317,
            1541.0500000013235,
            1547.7500000013479,
            1553.4500000013686,
            1553.6000000013692,
            1560.7500000013952,
            1562.2500000014006,
            1569.8500000014283,
            1570.900000001432,
            1573.900000001443,
            1575.000000001447,
            1575.2000000014477,
            1577.9500000014577,
            1579.150000001462,
            1588.8500000014974,
            1589.7000000015005,
            1589.9000000015012,
            1593.6500000015149,
            1594.3500000015174,
            1599.3500000015356,
            1601.950000001545,
            1602.750000001548,
            1606.2500000015607,
            1607.6000000015656,
            1608.1000000015674,
            1613.0000000015852,
            1617.350000001601,
            1617.350000001601,
            1621.0000000016144,
            1621.700000001617,
            1624.500000001627,
            1630.4000000016486,
            1633.2000000016587,
            1634.8500000016647,
            1636.30000000167,
            1638.250000001677,
            1642.6500000016931,
            1647.4000000017104,
            1647.9000000017122,
            1648.0500000017128,
            1649.0500000017164,
            1652.7500000017299,
            1657.9000000017486,
            1658.2000000017497,
            1665.4000000017759,
            1665.6000000017766,
            1674.3000000018083,
            1681.6000000018348,
            1684.3500000018448,
            1688.1000000018585,
            1692.0000000018726,
            1694.3500000018812,
            1694.6500000018823,
            1695.3000000018847,
            1695.9000000018868,
            1698.1000000018948,
            1702.6500000019114,
            1703.650000001915,
            1703.8000000019156,
            1704.3000000019174,
            1714.100000001953,
            1715.750000001959,
            1717.0500000019638,
            1721.250000001979,
            1723.0500000019856,
            1723.9500000019889,
            1727.4500000020016,
            1728.2000000020043,
            1729.2500000020082,
            1731.100000002015,
            1733.0000000020218,
            1733.7500000020245,
            1733.900000002025,
            1734.7500000020282,
            1737.8500000020395,
            1739.0500000020438,
            1742.2000000020553,
            1742.5000000020564,
            1743.6000000020604,
            1744.1500000020624,
            1745.2500000020664,
            1752.000000002091,
            1753.7500000020973,
            1760.5000000021219,
            1761.4000000021251,
            1764.3500000021359,
            1764.7500000021373,
            1771.8500000021631,
            1776.3500000021795,
            1784.70000000221,
            1796.800000002254,
            1797.0500000022548,
            1799.7500000022646,
            1801.6500000022716,
            1808.8500000022977,
            1809.0500000022985,
            1810.2500000023028,
            1818.4000000023325,
            1821.4500000023436,
            1826.1500000023607,
            1826.5500000023621,
            1827.350000002365,
            1828.2500000023683,
            1829.000000002371,
            1833.5500000023876,
            1838.350000002405,
            1841.9500000024182,
            1846.550000002435,
            1848.200000002441,
            1851.3000000024522,
            1854.250000002463,
            1855.7500000024684,
            1861.9000000024907,
            1865.850000002505,
            1869.5500000025186,
            1875.8000000025413,
            1877.2000000025464,
            1878.5000000025511,
            1878.9000000025526,
            1879.300000002554,
            1880.8000000025595,
            1884.9000000025744,
            1885.5000000025766,
            1892.6500000026026,
            1894.70000000261,
            1900.3500000026306,
            1908.150000002659,
            1909.800000002665,
            1912.2000000026737,
            1912.6000000026752,
            1916.0500000026877,
            1918.4500000026965,
            1924.0500000027168,
            1924.2000000027174,
            1927.3000000027287,
            1929.0000000027349,
            1929.2500000027358,
            1932.1500000027463,
            1935.8500000027598,
            1937.5000000027658,
            1938.0500000027678,
            1943.0000000027858,
            1943.1000000027861,
            1951.550000002817,
            1958.2500000028413,
            1969.8500000028835,
            1975.1500000029027,
            1977.3500000029107,
            1993.4000000029691,
            1999.2000000029902
        ]
    }
}